[
  {
    "author": "Formesam",
    "link_thumb": "https://live.staticflickr.com/65535/51787155533_fe5b0b8c73_o.gif",
    "link_bin": "https://github.com/lmbstudiocontact/mb4_0/raw/main/1052.bin",
    "id_bin": "1052",
    "list_language": [],
    "array_tags": [
      "red",
      "minimal",
      "marvel",
      "blue",
      "spiderman"
    ],
    "list_album": [
      {
        "id_album": "-1997428321",
        "link_thumb": "https://live.staticflickr.com/65535/51787155533_fe5b0b8c73_o.gif",
        "title": "Marvel"
      }
    ]
  },
  {
    "author": "Hide",
    "link_thumb": "https://live.staticflickr.com/65535/51786071897_ff9df44723_o.gif",
    "link_bin": "https://github.com/lmbstudiocontact/mb4_0/raw/main/10821.bin",
    "id_bin": "10821",
    "list_language": [],
    "array_tags": [
      "date",
      "digital",
      "movie",
      "spiderman",
      "battery"
    ],
    "list_album": [
      {
        "id_album": "-1997428321",
        "link_thumb": "https://live.staticflickr.com/65535/51786071897_ff9df44723_o.gif",
        "title": "Marvel"
      }
    ]
  },
  {
    "author": "leopercoelho",
    "link_thumb": "https://live.staticflickr.com/65535/51787507444_8c120c198e_o.gif",
    "link_bin": "https://github.com/lmbstudiocontact/mb4_0/raw/main/11146.bin",
    "id_bin": "11146",
    "list_language": [],
    "array_tags": [
      "spiderman"
    ],
    "list_album": [
      {
        "id_album": "-1997428321",
        "link_thumb": "https://live.staticflickr.com/65535/51787507444_8c120c198e_o.gif",
        "title": "Marvel"
      }
    ]
  },
  {
    "author": "giselevv",
    "link_thumb": "https://live.staticflickr.com/65535/51787770140_f50bdb9b06_o.gif",
    "link_bin": "https://github.com/lmbstudiocontact/mb4_48/raw/main/20106.bin",
    "id_bin": "20106",
    "list_language": [],
    "array_tags": [
      "digital",
      "date",
      "film",
      "battery",
      "spiderman"
    ],
    "list_album": [
      {
        "id_album": "-2075887794",
        "link_thumb": "https://live.staticflickr.com/65535/51787770140_f50bdb9b06_o.gif",
        "title": "Cartoon"
      }
    ]
  },
  {
    "author": "ville",
    "link_thumb": "https://live.staticflickr.com/65535/51787762235_8215d50191_o.gif",
    "link_bin": "https://github.com/lmbstudiocontact/mb4_6/raw/main/3342.bin",
    "id_bin": "3342",
    "list_language": [],
    "array_tags": [
      "spiderman"
    ],
    "list_album": [
      {
        "id_album": "74534672",
        "link_thumb": "https://live.staticflickr.com/65535/51787762235_8215d50191_o.gif",
        "title": "Movie"
      }
    ]
  },
  {
    "author": "TehMaat",
    "link_thumb": "https://live.staticflickr.com/65535/51787534154_0ee56ae91f_o.gif",
    "link_bin": "https://github.com/lmbstudiocontact/mb4_6/raw/main/3744.bin",
    "id_bin": "3744",
    "list_language": [],
    "array_tags": [
      "red",
      "cartoon",
      "spiderman"
    ],
    "list_album": [
      {
        "id_album": "-1997428321",
        "link_thumb": "https://live.staticflickr.com/65535/51787534154_0ee56ae91f_o.gif",
        "title": "Marvel"
      }
    ]
  },
  {
    "author": "T1MOXA",
    "link_thumb": "https://live.staticflickr.com/65535/51787777795_fe1e6a4b79_o.gif",
    "link_bin": "https://github.com/lmbstudiocontact/mb4_66/raw/main/4278.bin",
    "id_bin": "4278",
    "list_language": [],
    "array_tags": [
      "digital",
      "date",
      "marvel",
      "distance",
      "heartrate",
      "spiderman",
      "battery",
      "steps"
    ],
    "list_album": [
      {
        "id_album": "-2075887794",
        "link_thumb": "https://live.staticflickr.com/65535/51787777795_fe1e6a4b79_o.gif",
        "title": "Cartoon"
      }
    ]
  },
  {
    "author": "Alixinhzai",
    "link_thumb": "https://live.staticflickr.com/65535/51786915566_f3ab2e7540_o.gif",
    "link_bin": "https://github.com/lmbstudiocontact/mb4_66/raw/main/441.bin",
    "id_bin": "441",
    "list_language": [],
    "array_tags": [
      "date",
      "digital",
      "blackbackground",
      "spiderman",
      "steps"
    ],
    "list_album": [
      {
        "id_album": "-2075887794",
        "link_thumb": "https://live.staticflickr.com/65535/51786915566_f3ab2e7540_o.gif",
        "title": "Cartoon"
      }
    ]
  },
  {
    "author": "T1MOXA",
    "link_thumb": "https://live.staticflickr.com/65535/51787522759_9d1e96d4e9_o.gif",
    "link_bin": "https://github.com/lmbstudiocontact/mb4_66/raw/main/4519.bin",
    "id_bin": "4519",
    "list_language": [],
    "array_tags": [
      "digital",
      "date",
      "marvel",
      "distance",
      "heartrate",
      "spiderman",
      "battery",
      "steps"
    ],
    "list_album": [
      {
        "id_album": "-1997428321",
        "link_thumb": "https://live.staticflickr.com/65535/51787522759_9d1e96d4e9_o.gif",
        "title": "Marvel"
      }
    ]
  },
  {
    "author": "infamousip",
    "link_thumb": "https://live.staticflickr.com/65535/51786892661_8b6ffc41cd_o.gif",
    "link_bin": "https://github.com/lmbstudiocontact/mb4_66/raw/main/5051.bin",
    "id_bin": "5051",
    "list_language": [],
    "array_tags": [
      "digital",
      "date",
      "italian",
      "battery",
      "spiderman",
      "steps"
    ],
    "list_album": [
      {
        "id_album": "-2075887794",
        "link_thumb": "https://live.staticflickr.com/65535/51786892661_8b6ffc41cd_o.gif",
        "title": "Cartoon"
      }
    ]
  },
  {
    "author": "Avone",
    "link_thumb": "https://live.staticflickr.com/65535/51787521614_005ac68731_o.gif",
    "link_bin": "https://github.com/lmbstudiocontact/mb4_11/raw/main/9656.bin",
    "id_bin": "9656",
    "list_language": [],
    "array_tags": [
      "date",
      "digital",
      "heartrate",
      "battery",
      "spiderman",
      "day",
      "steps"
    ],
    "list_album": [
      {
        "id_album": "-1524915004",
        "link_thumb": "https://live.staticflickr.com/65535/51787521614_005ac68731_o.gif",
        "title": "Marvel_Animation"
      }
    ]
  },
  {
    "author": "akhmalcapcom",
    "link_thumb": "https://live.staticflickr.com/65535/51787758455_6348a4f82d_o.gif",
    "link_bin": "https://github.com/lmbstudiocontact/mb4_16/raw/main/16044.bin",
    "id_bin": "16044",
    "list_language": [],
    "array_tags": [
      "animated",
      "spiderman",
      "animation"
    ],
    "list_album": [
      {
        "id_album": "-1956005621",
        "link_thumb": "https://live.staticflickr.com/65535/51787758455_6348a4f82d_o.gif",
        "title": "None_2"
      }
    ]
  },
  {
    "author": "akhmalcapcom",
    "link_thumb": "https://live.staticflickr.com/65535/51786885111_a37b784f43_o.gif",
    "link_bin": "https://github.com/lmbstudiocontact/mb4_16/raw/main/16057.bin",
    "id_bin": "16057",
    "list_language": [],
    "array_tags": [
      "spiderman",
      "cute"
    ],
    "list_album": [
      {
        "id_album": "-1956005621",
        "link_thumb": "https://live.staticflickr.com/65535/51786885111_a37b784f43_o.gif",
        "title": "None_2"
      }
    ]
  },
  {
    "author": "Raay_Mr",
    "link_thumb": "https://live.staticflickr.com/65535/51787757630_681349767b_o.gif",
    "link_bin": "https://github.com/lmbstudiocontact/mb4_16/raw/main/16075.bin",
    "id_bin": "16075",
    "list_language": [],
    "array_tags": [
      "date",
      "aesthetic",
      "brazil",
      "distance",
      "pt",
      "data",
      "hora",
      "brasil",
      "battery",
      "spiderman",
      "br",
      "seconds",
      "floors",
      "top",
      "weather",
      "portugues",
      "popular",
      "passos",
      "digital",
      "heartrate",
      "semana",
      "calories",
      "steps",
      "analog",
      "marvel",
      "avengers"
    ],
    "list_album": [
      {
        "id_album": "-2075887794",
        "link_thumb": "https://live.staticflickr.com/65535/51787757630_681349767b_o.gif",
        "title": "Cartoon"
      }
    ]
  },
  {
    "author": "grazi_andrad",
    "link_thumb": "https://live.staticflickr.com/65535/51787505949_dd3fa85d8e_o.gif",
    "link_bin": "https://github.com/lmbstudiocontact/mb4_16/raw/main/16094.bin",
    "id_bin": "16094",
    "list_language": [],
    "array_tags": [
      "digital",
      "bateria",
      "spiderman",
      "passos"
    ],
    "list_album": [
      {
        "id_album": "-1956005621",
        "link_thumb": "https://live.staticflickr.com/65535/51787505949_dd3fa85d8e_o.gif",
        "title": "None_2"
      }
    ]
  },
  {
    "author": "Raay_Mr",
    "link_thumb": "https://live.staticflickr.com/65535/51787135858_f3b1181d29_o.gif",
    "link_bin": "https://github.com/lmbstudiocontact/mb4_16/raw/main/16174.bin",
    "id_bin": "16174",
    "list_language": [],
    "array_tags": [
      "date",
      "aesthetic",
      "brazil",
      "distance",
      "pt",
      "data",
      "hora",
      "brasil",
      "battery",
      "spiderman",
      "br",
      "seconds",
      "floors",
      "top",
      "weather",
      "portugues",
      "popular",
      "passos",
      "digital",
      "heartrate",
      "semana",
      "calories",
      "steps",
      "analog",
      "marvel"
    ],
    "list_album": [
      {
        "id_album": "2433880",
        "link_thumb": "https://live.staticflickr.com/65535/51787135858_f3b1181d29_o.gif",
        "title": "None"
      }
    ]
  },
  {
    "author": "Danielongo27",
    "link_thumb": "https://live.staticflickr.com/65535/51787500264_0dc273d921_o.gif",
    "link_bin": "https://github.com/lmbstudiocontact/mb4_16/raw/main/16460.bin",
    "id_bin": "16460",
    "list_language": [],
    "array_tags": [
      "red",
      "bateria",
      "marvel",
      "bluetooth",
      "blue",
      "spiderman",
      "battery",
      "azul"
    ],
    "list_album": [
      {
        "id_album": "-1956005621",
        "link_thumb": "https://live.staticflickr.com/65535/51787500264_0dc273d921_o.gif",
        "title": "None_2"
      }
    ]
  },
  {
    "author": "akhmalcapcom",
    "link_thumb": "https://live.staticflickr.com/65535/51787158723_c16d249050_o.gif",
    "link_bin": "https://github.com/lmbstudiocontact/mb4_17/raw/main/1260.bin",
    "id_bin": "1260",
    "list_language": [],
    "array_tags": [
      "red",
      "spiderman"
    ],
    "list_album": [
      {
        "id_album": "-1997428321",
        "link_thumb": "https://live.staticflickr.com/65535/51787158723_c16d249050_o.gif",
        "title": "Marvel"
      }
    ]
  },
  {
    "author": "Kalazior",
    "link_thumb": "https://live.staticflickr.com/65535/51787142293_2e656bf0ac_o.gif",
    "link_bin": "https://github.com/lmbstudiocontact/mb4_17/raw/main/12930.bin",
    "id_bin": "12930",
    "list_language": [],
    "array_tags": [
      "marvel",
      "ironman",
      "joker",
      "spiderman",
      "batman",
      "dc"
    ],
    "list_album": [
      {
        "id_album": "74534672",
        "link_thumb": "https://live.staticflickr.com/65535/51787142293_2e656bf0ac_o.gif",
        "title": "Movie"
      }
    ]
  },
  {
    "author": "grazi_andrad",
    "link_thumb": "https://live.staticflickr.com/65535/51787154213_6a90896013_o.gif",
    "link_bin": "https://github.com/lmbstudiocontact/mb4_16/raw/main/16932.bin",
    "id_bin": "16932",
    "list_language": [],
    "array_tags": [
      "digital",
      "date",
      "blue",
      "games",
      "battery",
      "spiderman",
      "steps"
    ],
    "list_album": [
      {
        "id_album": "-1956005621",
        "link_thumb": "https://live.staticflickr.com/65535/51787154213_6a90896013_o.gif",
        "title": "None_2"
      }
    ]
  },
  {
    "author": "BySciaa",
    "link_thumb": "https://live.staticflickr.com/65535/51787785625_1e77494128_o.gif",
    "link_bin": "https://github.com/lmbstudiocontact/mb4_21/raw/main/2172.bin",
    "id_bin": "2172",
    "list_language": [],
    "array_tags": [
      "marvel",
      "ironman",
      "miband4",
      "spiderman"
    ],
    "list_album": [
      {
        "id_album": "-1997428321",
        "link_thumb": "https://live.staticflickr.com/65535/51787785625_1e77494128_o.gif",
        "title": "Marvel"
      }
    ]
  },
  {
    "author": "BySciaa",
    "link_thumb": "https://live.staticflickr.com/65535/51786912256_afb94dae02_o.gif",
    "link_bin": "https://github.com/lmbstudiocontact/mb4_21/raw/main/2180.bin",
    "id_bin": "2180",
    "list_language": [],
    "array_tags": [
      "marvel",
      "avengers",
      "ironman",
      "miband4",
      "spiderman"
    ],
    "list_album": [
      {
        "id_album": "-1997428321",
        "link_thumb": "https://live.staticflickr.com/65535/51786912256_afb94dae02_o.gif",
        "title": "Marvel"
      }
    ]
  },
  {
    "author": "小洪昵称",
    "link_thumb": "https://live.staticflickr.com/65535/51786092537_f340d7e56d_o.gif",
    "link_bin": "https://github.com/lmbstudiocontact/mb4_21/raw/main/2305.bin",
    "id_bin": "2305",
    "list_language": [],
    "array_tags": [
      "spiderman"
    ],
    "list_album": [
      {
        "id_album": "-1997428321",
        "link_thumb": "https://live.staticflickr.com/65535/51786092537_f340d7e56d_o.gif",
        "title": "Marvel"
      }
    ]
  },
  {
    "author": "quangdan",
    "link_thumb": "https://live.staticflickr.com/65535/51786084302_bd19ac5304_o.gif",
    "link_bin": "https://github.com/lmbstudiocontact/mb4_25/raw/main/9561.bin",
    "id_bin": "9561",
    "list_language": [],
    "array_tags": [
      "marvel",
      "night",
      "dark",
      "spiderman"
    ],
    "list_album": [
      {
        "id_album": "-1997428321",
        "link_thumb": "https://live.staticflickr.com/65535/51786084302_bd19ac5304_o.gif",
        "title": "Marvel"
      }
    ]
  }
]