[
  {
    "author": "os.rodrigooliveira",
    "link_thumb": "https://live.staticflickr.com/65535/51787764895_510fc956a0_o.gif",
    "link_bin": "https://github.com/lmbstudiocontact/mb4_0/raw/main/10442.bin",
    "id_bin": "10442",
    "list_language": [],
    "array_tags": [
      "date",
      "distance",
      "weather",
      "calories",
      "battery",
      "steps"
    ],
    "list_album": [
      {
        "id_album": "-1968740153",
        "link_thumb": "https://live.staticflickr.com/65535/51787764895_510fc956a0_o.gif",
        "title": "Nature"
      }
    ]
  },
  {
    "author": "mblazhev",
    "link_thumb": "https://live.staticflickr.com/65535/51786891516_8ff660bd5f_o.gif",
    "link_bin": "https://github.com/lmbstudiocontact/mb4_0/raw/main/10452.bin",
    "id_bin": "10452",
    "list_language": [],
    "array_tags": [
      "digital",
      "distance",
      "battery",
      "steps"
    ],
    "list_album": [
      {
        "id_album": "1633802201",
        "link_thumb": "https://live.staticflickr.com/65535/51786891516_8ff660bd5f_o.gif",
        "title": "Football Old_Animation"
      }
    ]
  },
  {
    "author": "sapfir_57",
    "link_thumb": "https://live.staticflickr.com/65535/51787144478_57bd1928dd_o.gif",
    "link_bin": "https://github.com/lmbstudiocontact/mb4_0/raw/main/10453.bin",
    "id_bin": "10453",
    "list_language": [],
    "array_tags": [
      "digital",
      "date",
      "distance",
      "heartrate",
      "battery",
      "steps"
    ],
    "list_album": [
      {
        "id_album": "807717335",
        "link_thumb": "https://live.staticflickr.com/65535/51787144478_57bd1928dd_o.gif",
        "title": "Animals"
      }
    ]
  },
  {
    "author": "livre3600",
    "link_thumb": "https://live.staticflickr.com/65535/51786074632_223722a716_o.gif",
    "link_bin": "https://github.com/lmbstudiocontact/mb4_0/raw/main/10478.bin",
    "id_bin": "10478",
    "list_language": [],
    "array_tags": [
      "digital",
      "distance",
      "battery"
    ],
    "list_album": [
      {
        "id_album": "-1437374559",
        "link_thumb": "https://live.staticflickr.com/65535/51786074632_223722a716_o.gif",
        "title": "Finn Mertens Cartoon"
      }
    ]
  },
  {
    "author": "Andreunto",
    "link_thumb": "https://live.staticflickr.com/65535/51787524469_d4fd40fb0a_o.gif",
    "link_bin": "https://github.com/lmbstudiocontact/mb4_0/raw/main/1048.bin",
    "id_bin": "1048",
    "list_language": [],
    "array_tags": [
      "digital",
      "date",
      "distance",
      "heartrate",
      "battery",
      "steps"
    ],
    "list_album": [
      {
        "id_album": "518493955",
        "link_thumb": "https://live.staticflickr.com/65535/51787524469_d4fd40fb0a_o.gif",
        "title": "Other 3"
      }
    ]
  },
  {
    "author": "poenux",
    "link_thumb": "https://live.staticflickr.com/65535/51787512869_edec214eb4_o.gif",
    "link_bin": "https://github.com/lmbstudiocontact/mb4_0/raw/main/10500.bin",
    "id_bin": "10500",
    "list_language": [],
    "array_tags": [
      "seconds",
      "floors",
      "distance",
      "battery"
    ],
    "list_album": [
      {
        "id_album": "518493954",
        "link_thumb": "https://live.staticflickr.com/65535/51787512869_edec214eb4_o.gif",
        "title": "Other 2"
      }
    ]
  },
  {
    "author": "secret245",
    "link_thumb": "https://live.staticflickr.com/65535/51786074347_7faa34896c_o.gif",
    "link_bin": "https://github.com/lmbstudiocontact/mb4_0/raw/main/10523.bin",
    "id_bin": "10523",
    "list_language": [],
    "array_tags": [
      "date",
      "digital",
      "analog",
      "seconds",
      "floors",
      "distance",
      "heartrate",
      "calories",
      "battery",
      "steps"
    ],
    "list_album": [
      {
        "id_album": "518493953",
        "link_thumb": "https://live.staticflickr.com/65535/51786074347_7faa34896c_o.gif",
        "title": "Other 1"
      }
    ]
  },
  {
    "author": "AndresM",
    "link_thumb": "https://live.staticflickr.com/65535/51787512619_d9f17349cd_o.gif",
    "link_bin": "https://github.com/lmbstudiocontact/mb4_0/raw/main/10544.bin",
    "id_bin": "10544",
    "list_language": [],
    "array_tags": [
      "digital",
      "date",
      "distance",
      "simple",
      "battery",
      "steps"
    ],
    "list_album": [
      {
        "id_album": "518493953",
        "link_thumb": "https://live.staticflickr.com/65535/51787512619_d9f17349cd_o.gif",
        "title": "Other 1"
      }
    ]
  },
  {
    "author": "mateusfbi",
    "link_thumb": "https://live.staticflickr.com/65535/51786890741_f2b9c15a5d_o.gif",
    "link_bin": "https://github.com/lmbstudiocontact/mb4_0/raw/main/10563.bin",
    "id_bin": "10563",
    "list_language": [],
    "array_tags": [
      "digital",
      "date",
      "marvel",
      "distance",
      "heartrate",
      "battery",
      "steps"
    ],
    "list_album": [
      {
        "id_album": "518493954",
        "link_thumb": "https://live.staticflickr.com/65535/51786890741_f2b9c15a5d_o.gif",
        "title": "Other 2"
      }
    ]
  },
  {
    "author": "mblazhev",
    "link_thumb": "https://live.staticflickr.com/65535/51787512419_81cf32597e_o.gif",
    "link_bin": "https://github.com/lmbstudiocontact/mb4_0/raw/main/10569.bin",
    "id_bin": "10569",
    "list_language": [],
    "array_tags": [
      "digital",
      "date",
      "distance",
      "battery",
      "steps"
    ],
    "list_album": [
      {
        "id_album": "-975585370",
        "link_thumb": "https://live.staticflickr.com/65535/51787512419_81cf32597e_o.gif",
        "title": "Other 1_Animation"
      }
    ]
  },
  {
    "author": "Formesam",
    "link_thumb": "https://live.staticflickr.com/65535/51786085447_e548d5a46c_o.gif",
    "link_bin": "https://github.com/lmbstudiocontact/mb4_0/raw/main/1057.bin",
    "id_bin": "1057",
    "list_language": [],
    "array_tags": [
      "digital",
      "date",
      "distance",
      "color",
      "heartrate",
      "calories",
      "battery",
      "steps",
      "analog",
      "seconds",
      "floors",
      "weather"
    ],
    "list_album": [
      {
        "id_album": "518493955",
        "link_thumb": "https://live.staticflickr.com/65535/51786085447_e548d5a46c_o.gif",
        "title": "Other 3"
      }
    ]
  },
  {
    "author": "LastRush",
    "link_thumb": "https://live.staticflickr.com/65535/51786890616_b84fb53922_o.gif",
    "link_bin": "https://github.com/lmbstudiocontact/mb4_0/raw/main/10583.bin",
    "id_bin": "10583",
    "list_language": [],
    "array_tags": [
      "date",
      "digital",
      "distance",
      "battery",
      "steps"
    ],
    "list_album": [
      {
        "id_album": "518493953",
        "link_thumb": "https://live.staticflickr.com/65535/51786890616_b84fb53922_o.gif",
        "title": "Other 1"
      }
    ]
  },
  {
    "author": "GPS",
    "link_thumb": "https://live.staticflickr.com/65535/51787512174_77a1559601_o.gif",
    "link_bin": "https://github.com/lmbstudiocontact/mb4_0/raw/main/10590.bin",
    "id_bin": "10590",
    "list_language": [],
    "array_tags": [
      "digital",
      "date",
      "distance",
      "heartrate",
      "calories",
      "battery"
    ],
    "list_album": [
      {
        "id_album": "63410260",
        "link_thumb": "https://live.staticflickr.com/65535/51787512174_77a1559601_o.gif",
        "title": "Anime"
      }
    ]
  },
  {
    "author": "GPS",
    "link_thumb": "https://live.staticflickr.com/65535/51786073732_facaece44f_o.gif",
    "link_bin": "https://github.com/lmbstudiocontact/mb4_0/raw/main/10591.bin",
    "id_bin": "10591",
    "list_language": [],
    "array_tags": [
      "digital",
      "date",
      "distance",
      "heartrate",
      "calories",
      "battery",
      "steps"
    ],
    "list_album": [
      {
        "id_album": "63410260",
        "link_thumb": "https://live.staticflickr.com/65535/51786073732_facaece44f_o.gif",
        "title": "Anime"
      }
    ]
  },
  {
    "author": "Formesam",
    "link_thumb": "https://live.staticflickr.com/65535/51787155398_7d961f13dd_o.gif",
    "link_bin": "https://github.com/lmbstudiocontact/mb4_0/raw/main/1061.bin",
    "id_bin": "1061",
    "list_language": [],
    "array_tags": [
      "digital",
      "date",
      "analog",
      "seconds",
      "distance",
      "battery",
      "steps"
    ],
    "list_album": [
      {
        "id_album": "-274520792",
        "link_thumb": "https://live.staticflickr.com/65535/51787155398_7d961f13dd_o.gif",
        "title": "Other 3_Animation"
      }
    ]
  },
  {
    "author": "mateusfbi",
    "link_thumb": "https://live.staticflickr.com/65535/51786890011_b8ca5c5cb7_o.gif",
    "link_bin": "https://github.com/lmbstudiocontact/mb4_0/raw/main/10621.bin",
    "id_bin": "10621",
    "list_language": [],
    "array_tags": [
      "digital",
      "date",
      "marvel",
      "distance",
      "heartrate",
      "calories",
      "steps"
    ],
    "list_album": [
      {
        "id_album": "518493954",
        "link_thumb": "https://live.staticflickr.com/65535/51786890011_b8ca5c5cb7_o.gif",
        "title": "Other 2"
      }
    ]
  },
  {
    "author": "Bios",
    "link_thumb": "https://live.staticflickr.com/65535/51786073252_c92e633c8e_o.gif",
    "link_bin": "https://github.com/lmbstudiocontact/mb4_0/raw/main/10624.bin",
    "id_bin": "10624",
    "list_language": [],
    "array_tags": [
      "digital",
      "date",
      "distance",
      "animated",
      "battery"
    ],
    "list_album": [
      {
        "id_album": "224945075",
        "link_thumb": "https://live.staticflickr.com/65535/51786073252_c92e633c8e_o.gif",
        "title": "Cartoon_Animation"
      }
    ]
  },
  {
    "author": "GPS",
    "link_thumb": "https://live.staticflickr.com/65535/51786073222_5b662d17ee_o.gif",
    "link_bin": "https://github.com/lmbstudiocontact/mb4_0/raw/main/10630.bin",
    "id_bin": "10630",
    "list_language": [],
    "array_tags": [
      "digital",
      "date",
      "distance",
      "heartrate",
      "calories",
      "battery",
      "steps"
    ],
    "list_album": [
      {
        "id_album": "63410260",
        "link_thumb": "https://live.staticflickr.com/65535/51786073222_5b662d17ee_o.gif",
        "title": "Anime"
      }
    ]
  },
  {
    "author": "GPS",
    "link_thumb": "https://live.staticflickr.com/65535/51787762895_4ef2a22a9b_o.gif",
    "link_bin": "https://github.com/lmbstudiocontact/mb4_0/raw/main/10632.bin",
    "id_bin": "10632",
    "list_language": [],
    "array_tags": [
      "digital",
      "date",
      "distance",
      "heartrate",
      "calories",
      "battery",
      "steps"
    ],
    "list_album": [
      {
        "id_album": "63410260",
        "link_thumb": "https://live.staticflickr.com/65535/51787762895_4ef2a22a9b_o.gif",
        "title": "Anime"
      }
    ]
  },
  {
    "author": "mblazhev",
    "link_thumb": "https://live.staticflickr.com/65535/51787511564_a4f00a257d_o.gif",
    "link_bin": "https://github.com/lmbstudiocontact/mb4_0/raw/main/10634.bin",
    "id_bin": "10634",
    "list_language": [],
    "array_tags": [
      "digital",
      "date",
      "basketball",
      "distance",
      "battery",
      "steps"
    ],
    "list_album": [
      {
        "id_album": "1633802201",
        "link_thumb": "https://live.staticflickr.com/65535/51787511564_a4f00a257d_o.gif",
        "title": "Football Old_Animation"
      }
    ]
  },
  {
    "author": "k48writer",
    "link_thumb": "https://live.staticflickr.com/65535/51786889711_a8a5108893_o.gif",
    "link_bin": "https://github.com/lmbstudiocontact/mb4_0/raw/main/10657.bin",
    "id_bin": "10657",
    "list_language": [],
    "array_tags": [
      "digital",
      "date",
      "distance",
      "heartrate",
      "calories",
      "battery",
      "steps"
    ],
    "list_album": [
      {
        "id_album": "518493954",
        "link_thumb": "https://live.staticflickr.com/65535/51786889711_a8a5108893_o.gif",
        "title": "Other 2"
      }
    ]
  },
  {
    "author": "HLV",
    "link_thumb": "https://live.staticflickr.com/65535/51786889706_b61f0ca518_o.gif",
    "link_bin": "https://github.com/lmbstudiocontact/mb4_0/raw/main/10658.bin",
    "id_bin": "10658",
    "list_language": [],
    "array_tags": [
      "date",
      "distance",
      "battery",
      "steps"
    ],
    "list_album": [
      {
        "id_album": "2219708",
        "link_thumb": "https://live.staticflickr.com/65535/51786889706_b61f0ca518_o.gif",
        "title": "Girl"
      }
    ]
  },
  {
    "author": "shymik",
    "link_thumb": "https://live.staticflickr.com/65535/51787142588_a4be5128e8_o.gif",
    "link_bin": "https://github.com/lmbstudiocontact/mb4_0/raw/main/10678.bin",
    "id_bin": "10678",
    "list_language": [],
    "array_tags": [
      "digital",
      "date",
      "distance",
      "heartrate",
      "calories",
      "battery",
      "steps"
    ],
    "list_album": [
      {
        "id_album": "518493954",
        "link_thumb": "https://live.staticflickr.com/65535/51787142588_a4be5128e8_o.gif",
        "title": "Other 2"
      }
    ]
  },
  {
    "author": "mblazhev",
    "link_thumb": "https://live.staticflickr.com/65535/51787762495_4c8e44c103_o.gif",
    "link_bin": "https://github.com/lmbstudiocontact/mb4_0/raw/main/10685.bin",
    "id_bin": "10685",
    "list_language": [],
    "array_tags": [
      "digital",
      "date",
      "distance",
      "heartrate",
      "steps"
    ],
    "list_album": [
      {
        "id_album": "1381221108",
        "link_thumb": "https://live.staticflickr.com/65535/51787762495_4c8e44c103_o.gif",
        "title": "Football Old"
      }
    ]
  },
  {
    "author": "HaZk0l0k0",
    "link_thumb": "https://live.staticflickr.com/65535/51787155213_b32024a7df_o.gif",
    "link_bin": "https://github.com/lmbstudiocontact/mb4_0/raw/main/1069.bin",
    "id_bin": "1069",
    "list_language": [],
    "array_tags": [
      "digital",
      "date",
      "distance",
      "steps"
    ],
    "list_album": [
      {
        "id_album": "1381221108",
        "link_thumb": "https://live.staticflickr.com/65535/51787155213_b32024a7df_o.gif",
        "title": "Football Old"
      }
    ]
  },
  {
    "author": "Monisaisabel",
    "link_thumb": "https://live.staticflickr.com/65535/51787142488_9dd813c782_o.gif",
    "link_bin": "https://github.com/lmbstudiocontact/mb4_0/raw/main/10694.bin",
    "id_bin": "10694",
    "list_language": [],
    "array_tags": [
      "digital",
      "distance",
      "heartrate",
      "weather",
      "battery",
      "steps"
    ],
    "list_album": [
      {
        "id_album": "518493954",
        "link_thumb": "https://live.staticflickr.com/65535/51787142488_9dd813c782_o.gif",
        "title": "Other 2"
      }
    ]
  },
  {
    "author": "GPS",
    "link_thumb": "https://live.staticflickr.com/65535/51787762310_b5d9da5aa7_o.gif",
    "link_bin": "https://github.com/lmbstudiocontact/mb4_0/raw/main/10701.bin",
    "id_bin": "10701",
    "list_language": [],
    "array_tags": [
      "digital",
      "date",
      "distance",
      "heartrate",
      "battery",
      "steps"
    ],
    "list_album": [
      {
        "id_album": "63410260",
        "link_thumb": "https://live.staticflickr.com/65535/51787762310_b5d9da5aa7_o.gif",
        "title": "Anime"
      }
    ]
  },
  {
    "author": "GPS",
    "link_thumb": "https://live.staticflickr.com/65535/51787510999_27c4d15f49_o.gif",
    "link_bin": "https://github.com/lmbstudiocontact/mb4_0/raw/main/10702.bin",
    "id_bin": "10702",
    "list_language": [],
    "array_tags": [
      "date",
      "digital",
      "distance",
      "heartrate",
      "calories",
      "battery",
      "steps"
    ],
    "list_album": [
      {
        "id_album": "63410260",
        "link_thumb": "https://live.staticflickr.com/65535/51787510999_27c4d15f49_o.gif",
        "title": "Anime"
      }
    ]
  },
  {
    "author": "GPS",
    "link_thumb": "https://live.staticflickr.com/65535/51786889381_6cb9bfbbf3_o.gif",
    "link_bin": "https://github.com/lmbstudiocontact/mb4_0/raw/main/10703.bin",
    "id_bin": "10703",
    "list_language": [],
    "array_tags": [
      "date",
      "digital",
      "distance",
      "heartrate",
      "calories",
      "battery"
    ],
    "list_album": [
      {
        "id_album": "63410260",
        "link_thumb": "https://live.staticflickr.com/65535/51786889381_6cb9bfbbf3_o.gif",
        "title": "Anime"
      }
    ]
  },
  {
    "author": "brunell0",
    "link_thumb": "https://live.staticflickr.com/65535/51786072457_f5f20c74dd_o.gif",
    "link_bin": "https://github.com/lmbstudiocontact/mb4_0/raw/main/10731.bin",
    "id_bin": "10731",
    "list_language": [],
    "array_tags": [
      "digital",
      "date",
      "distance",
      "heartrate",
      "calories",
      "battery",
      "steps"
    ],
    "list_album": [
      {
        "id_album": "807717335",
        "link_thumb": "https://live.staticflickr.com/65535/51786072457_f5f20c74dd_o.gif",
        "title": "Animals"
      }
    ]
  },
  {
    "author": "thiagoliker",
    "link_thumb": "https://live.staticflickr.com/65535/51786072432_0114f71941_o.gif",
    "link_bin": "https://github.com/lmbstudiocontact/mb4_0/raw/main/10736.bin",
    "id_bin": "10736",
    "list_language": [],
    "array_tags": [
      "digital",
      "distance",
      "heartrate",
      "calories",
      "battery",
      "steps"
    ],
    "list_album": [
      {
        "id_album": "1522430567",
        "link_thumb": "https://live.staticflickr.com/65535/51786072432_0114f71941_o.gif",
        "title": "Other 2_Animation"
      }
    ]
  },
  {
    "author": "GPS",
    "link_thumb": "https://live.staticflickr.com/65535/51786072347_f98a746a5c_o.gif",
    "link_bin": "https://github.com/lmbstudiocontact/mb4_0/raw/main/10748.bin",
    "id_bin": "10748",
    "list_language": [],
    "array_tags": [
      "date",
      "digital",
      "distance",
      "heartrate",
      "calories",
      "battery",
      "steps"
    ],
    "list_album": [
      {
        "id_album": "63410260",
        "link_thumb": "https://live.staticflickr.com/65535/51786072347_f98a746a5c_o.gif",
        "title": "Anime"
      }
    ]
  },
  {
    "author": "GPS",
    "link_thumb": "https://live.staticflickr.com/65535/51787510574_d5679f6cbf_o.gif",
    "link_bin": "https://github.com/lmbstudiocontact/mb4_0/raw/main/10749.bin",
    "id_bin": "10749",
    "list_language": [],
    "array_tags": [
      "date",
      "digital",
      "distance",
      "heartrate",
      "calories",
      "battery",
      "steps"
    ],
    "list_album": [
      {
        "id_album": "63410260",
        "link_thumb": "https://live.staticflickr.com/65535/51787510574_d5679f6cbf_o.gif",
        "title": "Anime"
      }
    ]
  },
  {
    "author": "HLV",
    "link_thumb": "https://live.staticflickr.com/65535/51787761570_670e0a7386_o.gif",
    "link_bin": "https://github.com/lmbstudiocontact/mb4_0/raw/main/10800.bin",
    "id_bin": "10800",
    "list_language": [],
    "array_tags": [
      "digital",
      "date",
      "distance",
      "battery",
      "steps"
    ],
    "list_album": [
      {
        "id_album": "63410260",
        "link_thumb": "https://live.staticflickr.com/65535/51787761570_670e0a7386_o.gif",
        "title": "Anime"
      }
    ]
  },
  {
    "author": "ErenTry",
    "link_thumb": "https://live.staticflickr.com/65535/51786071962_33504f8d32_o.gif",
    "link_bin": "https://github.com/lmbstudiocontact/mb4_0/raw/main/10811.bin",
    "id_bin": "10811",
    "list_language": [],
    "array_tags": [
      "digital",
      "date",
      "game",
      "distance",
      "bluetooth",
      "fallout",
      "heartrate",
      "turkish",
      "battery",
      "steps"
    ],
    "list_album": [
      {
        "id_album": "1522430567",
        "link_thumb": "https://live.staticflickr.com/65535/51786071962_33504f8d32_o.gif",
        "title": "Other 2_Animation"
      }
    ]
  },
  {
    "author": "Nexoreon",
    "link_thumb": "https://live.staticflickr.com/65535/51787523339_124f735417_o.gif",
    "link_bin": "https://github.com/lmbstudiocontact/mb4_0/raw/main/1083.bin",
    "id_bin": "1083",
    "list_language": [],
    "array_tags": [
      "date",
      "distance",
      "russian",
      "heartrate",
      "english",
      "calories",
      "battery",
      "steps"
    ],
    "list_album": [
      {
        "id_album": "518493955",
        "link_thumb": "https://live.staticflickr.com/65535/51787523339_124f735417_o.gif",
        "title": "Other 3"
      }
    ]
  },
  {
    "author": "namhv94",
    "link_thumb": "https://live.staticflickr.com/65535/51787761205_990bb1cfd3_o.gif",
    "link_bin": "https://github.com/lmbstudiocontact/mb4_0/raw/main/10845.bin",
    "id_bin": "10845",
    "list_language": [],
    "array_tags": [
      "date",
      "distance",
      "battery",
      "steps"
    ],
    "list_album": [
      {
        "id_album": "518493954",
        "link_thumb": "https://live.staticflickr.com/65535/51787761205_990bb1cfd3_o.gif",
        "title": "Other 2"
      }
    ]
  },
  {
    "author": "TUNGXIAOMI",
    "link_thumb": "https://live.staticflickr.com/65535/51787761175_8f7e5ca22e_o.gif",
    "link_bin": "https://github.com/lmbstudiocontact/mb4_0/raw/main/10850.bin",
    "id_bin": "10850",
    "list_language": [],
    "array_tags": [
      "digital",
      "distance",
      "weather",
      "calories"
    ],
    "list_album": [
      {
        "id_album": "518493954",
        "link_thumb": "https://live.staticflickr.com/65535/51787761175_8f7e5ca22e_o.gif",
        "title": "Other 2"
      }
    ]
  },
  {
    "author": "Gianglun1992",
    "link_thumb": "https://live.staticflickr.com/65535/51786071667_e7d3973d60_o.gif",
    "link_bin": "https://github.com/lmbstudiocontact/mb4_0/raw/main/10858.bin",
    "id_bin": "10858",
    "list_language": [],
    "array_tags": [
      "digital",
      "date",
      "distance",
      "heartrate",
      "calories",
      "battery",
      "steps"
    ],
    "list_album": [
      {
        "id_album": "518493954",
        "link_thumb": "https://live.staticflickr.com/65535/51786071667_e7d3973d60_o.gif",
        "title": "Other 2"
      }
    ]
  },
  {
    "author": "mad max",
    "link_thumb": "https://live.staticflickr.com/65535/51786887976_b5b08d830b_o.gif",
    "link_bin": "https://github.com/lmbstudiocontact/mb4_0/raw/main/10892.bin",
    "id_bin": "10892",
    "list_language": [],
    "array_tags": [
      "digital",
      "date",
      "seconds",
      "distance",
      "heartrate",
      "battery",
      "steps"
    ],
    "list_album": [
      {
        "id_album": "518493954",
        "link_thumb": "https://live.staticflickr.com/65535/51786887976_b5b08d830b_o.gif",
        "title": "Other 2"
      }
    ]
  },
  {
    "author": "mad max",
    "link_thumb": "https://live.staticflickr.com/65535/51787760795_9b2b1f3c5d_o.gif",
    "link_bin": "https://github.com/lmbstudiocontact/mb4_0/raw/main/10894.bin",
    "id_bin": "10894",
    "list_language": [],
    "array_tags": [
      "digital",
      "date",
      "seconds",
      "distance",
      "heartrate",
      "battery",
      "steps"
    ],
    "list_album": [
      {
        "id_album": "518493954",
        "link_thumb": "https://live.staticflickr.com/65535/51787760795_9b2b1f3c5d_o.gif",
        "title": "Other 2"
      }
    ]
  },
  {
    "author": "mad max",
    "link_thumb": "https://live.staticflickr.com/65535/51786071292_86eedd6266_o.gif",
    "link_bin": "https://github.com/lmbstudiocontact/mb4_0/raw/main/10897.bin",
    "id_bin": "10897",
    "list_language": [],
    "array_tags": [
      "digital",
      "date",
      "seconds",
      "distance",
      "heartrate",
      "battery",
      "steps"
    ],
    "list_album": [
      {
        "id_album": "518493954",
        "link_thumb": "https://live.staticflickr.com/65535/51786071292_86eedd6266_o.gif",
        "title": "Other 2"
      }
    ]
  },
  {
    "author": "HLV",
    "link_thumb": "https://live.staticflickr.com/65535/51787509454_caa3eaf1ce_o.gif",
    "link_bin": "https://github.com/lmbstudiocontact/mb4_0/raw/main/10898.bin",
    "id_bin": "10898",
    "list_language": [],
    "array_tags": [
      "digital",
      "date",
      "distance",
      "battery",
      "steps"
    ],
    "list_album": [
      {
        "id_album": "518493954",
        "link_thumb": "https://live.staticflickr.com/65535/51787509454_caa3eaf1ce_o.gif",
        "title": "Other 2"
      }
    ]
  },
  {
    "author": "Alejandra",
    "link_thumb": "https://live.staticflickr.com/65535/51787509434_81c717949d_o.gif",
    "link_bin": "https://github.com/lmbstudiocontact/mb4_0/raw/main/10901.bin",
    "id_bin": "10901",
    "list_language": [],
    "array_tags": [
      "digital",
      "date",
      "distance",
      "battery",
      "steps"
    ],
    "list_album": [
      {
        "id_album": "1776510609",
        "link_thumb": "https://live.staticflickr.com/65535/51787509434_81c717949d_o.gif",
        "title": "Toy Story Footloose Cartoon"
      }
    ]
  },
  {
    "author": "Alejandra",
    "link_thumb": "https://live.staticflickr.com/65535/51786071207_a2cd2c2071_o.gif",
    "link_bin": "https://github.com/lmbstudiocontact/mb4_0/raw/main/10902.bin",
    "id_bin": "10902",
    "list_language": [],
    "array_tags": [
      "date",
      "digital",
      "floors",
      "distance",
      "battery",
      "steps"
    ],
    "list_album": [
      {
        "id_album": "68567713",
        "link_thumb": "https://live.staticflickr.com/65535/51786071207_a2cd2c2071_o.gif",
        "title": "Games"
      }
    ]
  },
  {
    "author": "mblazhev",
    "link_thumb": "https://live.staticflickr.com/65535/51787509304_b7d4175d13_o.gif",
    "link_bin": "https://github.com/lmbstudiocontact/mb4_0/raw/main/10911.bin",
    "id_bin": "10911",
    "list_language": [],
    "array_tags": [
      "digital",
      "date",
      "distance",
      "battery",
      "steps"
    ],
    "list_album": [
      {
        "id_album": "1633802201",
        "link_thumb": "https://live.staticflickr.com/65535/51787509304_b7d4175d13_o.gif",
        "title": "Football Old_Animation"
      }
    ]
  },
  {
    "author": "Gianglun1992",
    "link_thumb": "https://live.staticflickr.com/65535/51786071092_f59057dcd5_o.gif",
    "link_bin": "https://github.com/lmbstudiocontact/mb4_0/raw/main/10920.bin",
    "id_bin": "10920",
    "list_language": [],
    "array_tags": [
      "digital",
      "date",
      "distance",
      "heartrate",
      "battery",
      "steps"
    ],
    "list_album": [
      {
        "id_album": "518493954",
        "link_thumb": "https://live.staticflickr.com/65535/51786071092_f59057dcd5_o.gif",
        "title": "Other 2"
      }
    ]
  },
  {
    "author": "Rayner",
    "link_thumb": "https://live.staticflickr.com/65535/51787509189_40df12328b_o.gif",
    "link_bin": "https://github.com/lmbstudiocontact/mb4_0/raw/main/10928.bin",
    "id_bin": "10928",
    "list_language": [],
    "array_tags": [
      "digital",
      "analog",
      "distance",
      "steps"
    ],
    "list_album": [
      {
        "id_album": "518493954",
        "link_thumb": "https://live.staticflickr.com/65535/51787509189_40df12328b_o.gif",
        "title": "Other 2"
      }
    ]
  },
  {
    "author": "Rayner",
    "link_thumb": "https://live.staticflickr.com/65535/51786070982_9382449663_o.gif",
    "link_bin": "https://github.com/lmbstudiocontact/mb4_0/raw/main/10930.bin",
    "id_bin": "10930",
    "list_language": [],
    "array_tags": [
      "analog",
      "distance",
      "heartrate",
      "weather"
    ],
    "list_album": [
      {
        "id_album": "518493954",
        "link_thumb": "https://live.staticflickr.com/65535/51786070982_9382449663_o.gif",
        "title": "Other 2"
      }
    ]
  },
  {
    "author": "HLV",
    "link_thumb": "https://live.staticflickr.com/65535/51787509099_cb3f6a779c_o.gif",
    "link_bin": "https://github.com/lmbstudiocontact/mb4_0/raw/main/10945.bin",
    "id_bin": "10945",
    "list_language": [],
    "array_tags": [
      "digital",
      "date",
      "distance",
      "battery",
      "steps"
    ],
    "list_album": [
      {
        "id_album": "-1968740153",
        "link_thumb": "https://live.staticflickr.com/65535/51787509099_cb3f6a779c_o.gif",
        "title": "Nature"
      }
    ]
  }
]