[
  {
    "author": "vanness5059",
    "link_thumb": "https://live.staticflickr.com/65535/51671501966_d586e43815_o.gif",
    "link_bin": "https://github.com/lmbstudiocontact/mb4_1/raw/main/17077.bin",
    "id_bin": "17077",
    "list_language": [],
    "array_tags": [
      "digital",
      "analog",
      "seconds",
      "distance",
      "heartrate",
      "calories",
      "battery"
    ],
    "list_album": [
      {
        "id_album": "2433880",
        "link_thumb": "https://live.staticflickr.com/65535/51671501966_d586e43815_o.gif",
        "title": "None"
      }
    ]
  },
  {
    "author": "ahmedsheme",
    "link_thumb": "https://live.staticflickr.com/65535/51671502641_2d1703fbe5_o.gif",
    "link_bin": "https://github.com/lmbstudiocontact/mb4_1/raw/main/17083.bin",
    "id_bin": "17083",
    "list_language": [],
    "array_tags": [
      "date",
      "digital",
      "analog",
      "distance",
      "heartrate",
      "steps"
    ],
    "list_album": [
      {
        "id_album": "2433880",
        "link_thumb": "https://live.staticflickr.com/65535/51671502641_2d1703fbe5_o.gif",
        "title": "None"
      }
    ]
  },
  {
    "author": "TinoCet",
    "link_thumb": "https://live.staticflickr.com/65535/51670706417_086cf8f37f_o.gif",
    "link_bin": "https://github.com/lmbstudiocontact/mb4_1/raw/main/17132.bin",
    "id_bin": "17132",
    "list_language": [],
    "array_tags": [
      "digital",
      "date",
      "analog",
      "seconds",
      "heartrate",
      "battery",
      "steps"
    ],
    "list_album": [
      {
        "id_album": "2433880",
        "link_thumb": "https://live.staticflickr.com/65535/51670706417_086cf8f37f_o.gif",
        "title": "None"
      }
    ]
  },
  {
    "author": "alhlhli",
    "link_thumb": "https://live.staticflickr.com/65535/51671755303_2532455442_o.gif",
    "link_bin": "https://github.com/lmbstudiocontact/mb4_1/raw/main/17217.bin",
    "id_bin": "17217",
    "list_language": [],
    "array_tags": [
      "digital",
      "date",
      "analog",
      "seconds",
      "floors",
      "distance",
      "heartrate",
      "calories",
      "battery",
      "steps"
    ],
    "list_album": [
      {
        "id_album": "2433880",
        "link_thumb": "https://live.staticflickr.com/65535/51671755303_2532455442_o.gif",
        "title": "None"
      }
    ]
  },
  {
    "author": "mikerx",
    "link_thumb": "https://live.staticflickr.com/65535/51671758793_a965c71f12_o.gif",
    "link_bin": "https://github.com/lmbstudiocontact/mb4_1/raw/main/17252.bin",
    "id_bin": "17252",
    "list_language": [],
    "array_tags": [
      "analog",
      "blue"
    ],
    "list_album": [
      {
        "id_album": "2433880",
        "link_thumb": "https://live.staticflickr.com/65535/51671758793_a965c71f12_o.gif",
        "title": "None"
      }
    ]
  },
  {
    "author": "+M4rc0",
    "link_thumb": "https://live.staticflickr.com/65535/51671762408_bf5a1e1076_o.gif",
    "link_bin": "https://github.com/lmbstudiocontact/mb4_1/raw/main/17292.bin",
    "id_bin": "17292",
    "list_language": [],
    "array_tags": [
      "digital",
      "date",
      "analog",
      "battery",
      "steps"
    ],
    "list_album": [
      {
        "id_album": "2433880",
        "link_thumb": "https://live.staticflickr.com/65535/51671762408_bf5a1e1076_o.gif",
        "title": "None"
      }
    ]
  },
  {
    "author": "Tcontente",
    "link_thumb": "https://live.staticflickr.com/65535/51672408790_7a4e168886_o.gif",
    "link_bin": "https://github.com/lmbstudiocontact/mb4_1/raw/main/17431.bin",
    "id_bin": "17431",
    "list_language": [],
    "array_tags": [
      "date",
      "analog",
      "seconds",
      "heartrate",
      "calories",
      "battery",
      "steps"
    ],
    "list_album": [
      {
        "id_album": "2433880",
        "link_thumb": "https://live.staticflickr.com/65535/51672408790_7a4e168886_o.gif",
        "title": "None"
      }
    ]
  },
  {
    "author": "BlackFly",
    "link_thumb": "https://live.staticflickr.com/65535/51671792308_51e1f2a536_o.gif",
    "link_bin": "https://github.com/lmbstudiocontact/mb4_1/raw/main/17564.bin",
    "id_bin": "17564",
    "list_language": [],
    "array_tags": [
      "analog",
      "russian"
    ],
    "list_album": [
      {
        "id_album": "2433880",
        "link_thumb": "https://live.staticflickr.com/65535/51671792308_51e1f2a536_o.gif",
        "title": "None"
      }
    ]
  },
  {
    "author": "GodMutant",
    "link_thumb": "https://live.staticflickr.com/65535/51670750872_f41d552176_o.gif",
    "link_bin": "https://github.com/lmbstudiocontact/mb4_1/raw/main/17567.bin",
    "id_bin": "17567",
    "list_language": [],
    "array_tags": [
      "analog",
      "humor"
    ],
    "list_album": [
      {
        "id_album": "2433880",
        "link_thumb": "https://live.staticflickr.com/65535/51670750872_f41d552176_o.gif",
        "title": "None"
      }
    ]
  },
  {
    "author": "IsoHere",
    "link_thumb": "https://live.staticflickr.com/65535/51670755782_9ed599a7c8_o.gif",
    "link_bin": "https://github.com/lmbstudiocontact/mb4_1/raw/main/17608.bin",
    "id_bin": "17608",
    "list_language": [],
    "array_tags": [
      "date",
      "analog",
      "seconds",
      "battery",
      "steps"
    ],
    "list_album": [
      {
        "id_album": "2433880",
        "link_thumb": "https://live.staticflickr.com/65535/51670755782_9ed599a7c8_o.gif",
        "title": "None"
      }
    ]
  },
  {
    "author": "slyhunt",
    "link_thumb": "https://live.staticflickr.com/65535/51670759932_13e0a67f61_o.gif",
    "link_bin": "https://github.com/lmbstudiocontact/mb4_1/raw/main/17644.bin",
    "id_bin": "17644",
    "list_language": [],
    "array_tags": [
      "date",
      "digital",
      "analog",
      "seconds",
      "distance",
      "heartrate",
      "calories",
      "battery",
      "steps"
    ],
    "list_album": [
      {
        "id_album": "2433880",
        "link_thumb": "https://live.staticflickr.com/65535/51670759932_13e0a67f61_o.gif",
        "title": "None"
      }
    ]
  },
  {
    "author": "soyyo",
    "link_thumb": "https://live.staticflickr.com/65535/51671803668_60ed56f16b_o.gif",
    "link_bin": "https://github.com/lmbstudiocontact/mb4_1/raw/main/17666.bin",
    "id_bin": "17666",
    "list_language": [],
    "array_tags": [
      "digital",
      "date",
      "analog",
      "heartrate",
      "battery"
    ],
    "list_album": [
      {
        "id_album": "2433880",
        "link_thumb": "https://live.staticflickr.com/65535/51671803668_60ed56f16b_o.gif",
        "title": "None"
      }
    ]
  },
  {
    "author": ".Kosmik",
    "link_thumb": "https://live.staticflickr.com/65535/51672243314_5eb672b7ef_o.gif",
    "link_bin": "https://github.com/lmbstudiocontact/mb4_1/raw/main/17667.bin",
    "id_bin": "17667",
    "list_language": [],
    "array_tags": [
      "analog",
      "heartrate",
      "battery",
      "steps"
    ],
    "list_album": [
      {
        "id_album": "2433880",
        "link_thumb": "https://live.staticflickr.com/65535/51672243314_5eb672b7ef_o.gif",
        "title": "None"
      }
    ]
  },
  {
    "author": "soyyo",
    "link_thumb": "https://live.staticflickr.com/65535/51671566931_6d49a4deb1_o.gif",
    "link_bin": "https://github.com/lmbstudiocontact/mb4_1/raw/main/17698.bin",
    "id_bin": "17698",
    "list_language": [],
    "array_tags": [
      "digital",
      "date",
      "analog",
      "heartrate",
      "battery",
      "steps"
    ],
    "list_album": [
      {
        "id_album": "2433880",
        "link_thumb": "https://live.staticflickr.com/65535/51671566931_6d49a4deb1_o.gif",
        "title": "None"
      }
    ]
  },
  {
    "author": "soyyo",
    "link_thumb": "https://live.staticflickr.com/65535/51671807068_be5864ee64_o.gif",
    "link_bin": "https://github.com/lmbstudiocontact/mb4_1/raw/main/17700.bin",
    "id_bin": "17700",
    "list_language": [],
    "array_tags": [
      "digital",
      "date",
      "analog",
      "heartrate",
      "battery",
      "steps"
    ],
    "list_album": [
      {
        "id_album": "2433880",
        "link_thumb": "https://live.staticflickr.com/65535/51671807068_be5864ee64_o.gif",
        "title": "None"
      }
    ]
  },
  {
    "author": "Lord-Sarakir",
    "link_thumb": "https://live.staticflickr.com/65535/51670767297_cec7d7bb78_o.gif",
    "link_bin": "https://github.com/lmbstudiocontact/mb4_1/raw/main/17731.bin",
    "id_bin": "17731",
    "list_language": [],
    "array_tags": [
      "date",
      "analog",
      "starwars",
      "distance",
      "heartrate",
      "battery",
      "steps"
    ],
    "list_album": [
      {
        "id_album": "2433880",
        "link_thumb": "https://live.staticflickr.com/65535/51670767297_cec7d7bb78_o.gif",
        "title": "None"
      }
    ]
  },
  {
    "author": "Lord-Sarakir",
    "link_thumb": "https://live.staticflickr.com/65535/51670767407_981283c96d_o.gif",
    "link_bin": "https://github.com/lmbstudiocontact/mb4_1/raw/main/17732.bin",
    "id_bin": "17732",
    "list_language": [],
    "array_tags": [
      "date",
      "analog",
      "starwars",
      "distance",
      "heartrate",
      "battery",
      "steps"
    ],
    "list_album": [
      {
        "id_album": "2433880",
        "link_thumb": "https://live.staticflickr.com/65535/51670767407_981283c96d_o.gif",
        "title": "None"
      }
    ]
  },
  {
    "author": "mikerx",
    "link_thumb": "https://live.staticflickr.com/65535/51672442950_9959a02f61_o.gif",
    "link_bin": "https://github.com/lmbstudiocontact/mb4_1/raw/main/17777.bin",
    "id_bin": "17777",
    "list_language": [],
    "array_tags": [
      "analog",
      "color",
      "blue"
    ],
    "list_album": [
      {
        "id_album": "2433880",
        "link_thumb": "https://live.staticflickr.com/65535/51672442950_9959a02f61_o.gif",
        "title": "None"
      }
    ]
  },
  {
    "author": "lejjandary",
    "link_thumb": "https://live.staticflickr.com/65535/51672255404_411b0724ac_o.gif",
    "link_bin": "https://github.com/lmbstudiocontact/mb4_1/raw/main/17806.bin",
    "id_bin": "17806",
    "list_language": [],
    "array_tags": [
      "digital",
      "analog",
      "game",
      "distance"
    ],
    "list_album": [
      {
        "id_album": "2433880",
        "link_thumb": "https://live.staticflickr.com/65535/51672255404_411b0724ac_o.gif",
        "title": "None"
      }
    ]
  },
  {
    "author": "never_say_no",
    "link_thumb": "https://live.staticflickr.com/65535/51670774072_a092f4ba5d_o.gif",
    "link_bin": "https://github.com/lmbstudiocontact/mb4_1/raw/main/1781.bin",
    "id_bin": "1781",
    "list_language": [],
    "array_tags": [
      "date",
      "digital",
      "analog",
      "seconds",
      "floors",
      "distance",
      "heartrate",
      "weather",
      "calories",
      "battery",
      "steps"
    ],
    "list_album": [
      {
        "id_album": "518493955",
        "link_thumb": "https://live.staticflickr.com/65535/51670774072_a092f4ba5d_o.gif",
        "title": "Other 3"
      }
    ]
  },
  {
    "author": "kleber0a0m",
    "link_thumb": "https://live.staticflickr.com/65535/51671816323_ab8d03896c_o.gif",
    "link_bin": "https://github.com/lmbstudiocontact/mb4_1/raw/main/17810.bin",
    "id_bin": "17810",
    "list_language": [],
    "array_tags": [
      "digital",
      "date",
      "analog",
      "seconds",
      "battery",
      "steps"
    ],
    "list_album": [
      {
        "id_album": "2433880",
        "link_thumb": "https://live.staticflickr.com/65535/51671816323_ab8d03896c_o.gif",
        "title": "None"
      }
    ]
  },
  {
    "author": "kleber0a0m",
    "link_thumb": "https://live.staticflickr.com/65535/51672446850_25dd187d6b_o.gif",
    "link_bin": "https://github.com/lmbstudiocontact/mb4_1/raw/main/17811.bin",
    "id_bin": "17811",
    "list_language": [],
    "array_tags": [
      "digital",
      "date",
      "analog",
      "seconds",
      "distance",
      "calories",
      "battery",
      "steps"
    ],
    "list_album": [
      {
        "id_album": "2433880",
        "link_thumb": "https://live.staticflickr.com/65535/51672446850_25dd187d6b_o.gif",
        "title": "None"
      }
    ]
  },
  {
    "author": "soltanisamir",
    "link_thumb": "https://live.staticflickr.com/65535/51671817198_897947d0fa_o.gif",
    "link_bin": "https://github.com/lmbstudiocontact/mb4_1/raw/main/17818.bin",
    "id_bin": "17818",
    "list_language": [],
    "array_tags": [
      "date",
      "analog",
      "distance",
      "heartrate",
      "steps"
    ],
    "list_album": [
      {
        "id_album": "2433880",
        "link_thumb": "https://live.staticflickr.com/65535/51671817198_897947d0fa_o.gif",
        "title": "None"
      }
    ]
  },
  {
    "author": "mrezaznd",
    "link_thumb": "https://live.staticflickr.com/65535/51671832428_1ce529113d_o.gif",
    "link_bin": "https://github.com/lmbstudiocontact/mb4_1/raw/main/17921.bin",
    "id_bin": "17921",
    "list_language": [],
    "array_tags": [
      "digital",
      "date",
      "analog",
      "seconds",
      "heartrate",
      "calories",
      "battery",
      "steps"
    ],
    "list_album": [
      {
        "id_album": "2433880",
        "link_thumb": "https://live.staticflickr.com/65535/51671832428_1ce529113d_o.gif",
        "title": "None"
      }
    ]
  },
  {
    "author": "soyyo",
    "link_thumb": "https://live.staticflickr.com/65535/51672463045_ee1323d899_o.gif",
    "link_bin": "https://github.com/lmbstudiocontact/mb4_1/raw/main/17922.bin",
    "id_bin": "17922",
    "list_language": [],
    "array_tags": [
      "digital",
      "date",
      "analog",
      "heartrate",
      "battery",
      "steps"
    ],
    "list_album": [
      {
        "id_album": "2433880",
        "link_thumb": "https://live.staticflickr.com/65535/51672463045_ee1323d899_o.gif",
        "title": "None"
      }
    ]
  },
  {
    "author": "soyyo",
    "link_thumb": "https://live.staticflickr.com/65535/51672273479_3c6b008c8c_o.gif",
    "link_bin": "https://github.com/lmbstudiocontact/mb4_1/raw/main/17932.bin",
    "id_bin": "17932",
    "list_language": [],
    "array_tags": [
      "digital",
      "date",
      "analog",
      "heartrate",
      "battery",
      "steps"
    ],
    "list_album": [
      {
        "id_album": "2433880",
        "link_thumb": "https://live.staticflickr.com/65535/51672273479_3c6b008c8c_o.gif",
        "title": "None"
      }
    ]
  },
  {
    "author": "soyyo",
    "link_thumb": "https://live.staticflickr.com/65535/51670792752_e7d186dcd6_o.gif",
    "link_bin": "https://github.com/lmbstudiocontact/mb4_1/raw/main/17939.bin",
    "id_bin": "17939",
    "list_language": [],
    "array_tags": [
      "digital",
      "date",
      "analog",
      "heartrate",
      "battery",
      "steps"
    ],
    "list_album": [
      {
        "id_album": "2433880",
        "link_thumb": "https://live.staticflickr.com/65535/51670792752_e7d186dcd6_o.gif",
        "title": "None"
      }
    ]
  },
  {
    "author": "EnderGuy32",
    "link_thumb": "https://live.staticflickr.com/65535/51670796372_e56cbefc47_o.gif",
    "link_bin": "https://github.com/lmbstudiocontact/mb4_1/raw/main/17965.bin",
    "id_bin": "17965",
    "list_language": [],
    "array_tags": [
      "date",
      "analog",
      "heartrate",
      "battery",
      "steps"
    ],
    "list_album": [
      {
        "id_album": "2433880",
        "link_thumb": "https://live.staticflickr.com/65535/51670796372_e56cbefc47_o.gif",
        "title": "None"
      }
    ]
  },
  {
    "author": "CzAlien",
    "link_thumb": "https://live.staticflickr.com/65535/51672469455_d824aa21f8_o.gif",
    "link_bin": "https://github.com/lmbstudiocontact/mb4_1/raw/main/17972.bin",
    "id_bin": "17972",
    "list_language": [],
    "array_tags": [
      "date",
      "analog",
      "english",
      "days",
      "battery",
      "steps",
      "czech"
    ],
    "list_album": [
      {
        "id_album": "2433880",
        "link_thumb": "https://live.staticflickr.com/65535/51672469455_d824aa21f8_o.gif",
        "title": "None"
      }
    ]
  },
  {
    "author": "soyyo",
    "link_thumb": "https://live.staticflickr.com/65535/51672278929_4af89d82db_o.gif",
    "link_bin": "https://github.com/lmbstudiocontact/mb4_1/raw/main/17976.bin",
    "id_bin": "17976",
    "list_language": [],
    "array_tags": [
      "digital",
      "date",
      "analog",
      "heartrate",
      "battery",
      "steps"
    ],
    "list_album": [
      {
        "id_album": "2433880",
        "link_thumb": "https://live.staticflickr.com/65535/51672278929_4af89d82db_o.gif",
        "title": "None"
      }
    ]
  },
  {
    "author": "mzo69",
    "link_thumb": "https://live.staticflickr.com/65535/51672470930_7e38f5d237_o.gif",
    "link_bin": "https://github.com/lmbstudiocontact/mb4_1/raw/main/17981.bin",
    "id_bin": "17981",
    "list_language": [],
    "array_tags": [
      "digital",
      "date",
      "analog"
    ],
    "list_album": [
      {
        "id_album": "2433880",
        "link_thumb": "https://live.staticflickr.com/65535/51672470930_7e38f5d237_o.gif",
        "title": "None"
      }
    ]
  },
  {
    "author": "soyyo",
    "link_thumb": "https://live.staticflickr.com/65535/51671841713_17c8f4a0eb_o.gif",
    "link_bin": "https://github.com/lmbstudiocontact/mb4_1/raw/main/17986.bin",
    "id_bin": "17986",
    "list_language": [],
    "array_tags": [
      "digital",
      "date",
      "analog",
      "heartrate",
      "battery",
      "steps"
    ],
    "list_album": [
      {
        "id_album": "2433880",
        "link_thumb": "https://live.staticflickr.com/65535/51671841713_17c8f4a0eb_o.gif",
        "title": "None"
      }
    ]
  },
  {
    "author": "CzAlien",
    "link_thumb": "https://live.staticflickr.com/65535/51670800242_dcffa8b90b_o.gif",
    "link_bin": "https://github.com/lmbstudiocontact/mb4_1/raw/main/17998.bin",
    "id_bin": "17998",
    "list_language": [],
    "array_tags": [
      "date",
      "analog",
      "seconds",
      "distance",
      "heartrate",
      "english",
      "days",
      "calories",
      "battery",
      "steps",
      "czech"
    ],
    "list_album": [
      {
        "id_album": "2433880",
        "link_thumb": "https://live.staticflickr.com/65535/51670800242_dcffa8b90b_o.gif",
        "title": "None"
      }
    ]
  },
  {
    "author": "soyyo",
    "link_thumb": "https://live.staticflickr.com/65535/51671843193_ce24350edf_o.gif",
    "link_bin": "https://github.com/lmbstudiocontact/mb4_1/raw/main/18003.bin",
    "id_bin": "18003",
    "list_language": [],
    "array_tags": [
      "digital",
      "date",
      "analog",
      "heartrate",
      "battery",
      "steps"
    ],
    "list_album": [
      {
        "id_album": "2433880",
        "link_thumb": "https://live.staticflickr.com/65535/51671843193_ce24350edf_o.gif",
        "title": "None"
      }
    ]
  },
  {
    "author": "soyyo",
    "link_thumb": "https://live.staticflickr.com/65535/51671603281_d9e35dce1b_o.gif",
    "link_bin": "https://github.com/lmbstudiocontact/mb4_1/raw/main/18004.bin",
    "id_bin": "18004",
    "list_language": [],
    "array_tags": [
      "digital",
      "date",
      "analog",
      "heartrate",
      "battery",
      "steps"
    ],
    "list_album": [
      {
        "id_album": "2433880",
        "link_thumb": "https://live.staticflickr.com/65535/51671603281_d9e35dce1b_o.gif",
        "title": "None"
      }
    ]
  },
  {
    "author": "DenisML",
    "link_thumb": "https://live.staticflickr.com/65535/51672081081_490e2a268e_o.gif",
    "link_bin": "https://github.com/lmbstudiocontact/mb4_10/raw/main/5622.bin",
    "id_bin": "5622",
    "list_language": [],
    "array_tags": [
      "digital",
      "date",
      "analog",
      "seconds",
      "battery"
    ],
    "list_album": [
      {
        "id_album": "2092863",
        "link_thumb": "https://live.staticflickr.com/65535/51672081081_490e2a268e_o.gif",
        "title": "Cars"
      }
    ]
  },
  {
    "author": "LuizFelipeSA",
    "link_thumb": "https://live.staticflickr.com/65535/51672081716_227eb8b96f_o.gif",
    "link_bin": "https://github.com/lmbstudiocontact/mb4_10/raw/main/5628.bin",
    "id_bin": "5628",
    "list_language": [],
    "array_tags": [
      "date",
      "analog",
      "floors",
      "distance",
      "heartrate",
      "weather",
      "calories",
      "battery"
    ],
    "list_album": [
      {
        "id_album": "63410260",
        "link_thumb": "https://live.staticflickr.com/65535/51672081716_227eb8b96f_o.gif",
        "title": "Anime"
      }
    ]
  },
  {
    "author": "kr333",
    "link_thumb": "https://live.staticflickr.com/65535/51671284502_17e6dbd0bb_o.gif",
    "link_bin": "https://github.com/lmbstudiocontact/mb4_10/raw/main/5660.bin",
    "id_bin": "5660",
    "list_language": [],
    "array_tags": [
      "analog"
    ],
    "list_album": [
      {
        "id_album": "518493955",
        "link_thumb": "https://live.staticflickr.com/65535/51671284502_17e6dbd0bb_o.gif",
        "title": "Other 3"
      }
    ]
  },
  {
    "author": "debianos174",
    "link_thumb": "https://live.staticflickr.com/65535/51671286472_b65086bcee_o.gif",
    "link_bin": "https://github.com/lmbstudiocontact/mb4_10/raw/main/5674.bin",
    "id_bin": "5674",
    "list_language": [],
    "array_tags": [
      "date",
      "analog",
      "battery",
      "steps"
    ],
    "list_album": [
      {
        "id_album": "-1907941713",
        "link_thumb": "https://live.staticflickr.com/65535/51671286472_b65086bcee_o.gif",
        "title": "People"
      }
    ]
  },
  {
    "author": "denchu",
    "link_thumb": "https://live.staticflickr.com/65535/51672958930_197200bb9f_o.gif",
    "link_bin": "https://github.com/lmbstudiocontact/mb4_10/raw/main/5687.bin",
    "id_bin": "5687",
    "list_language": [],
    "array_tags": [
      "digital",
      "date",
      "analog",
      "seconds",
      "heartrate",
      "battery",
      "steps"
    ],
    "list_album": [
      {
        "id_album": "518493955",
        "link_thumb": "https://live.staticflickr.com/65535/51672958930_197200bb9f_o.gif",
        "title": "Other 3"
      }
    ]
  },
  {
    "author": "grknbrs",
    "link_thumb": "https://live.staticflickr.com/65535/51672093686_f430b32a56_o.gif",
    "link_bin": "https://github.com/lmbstudiocontact/mb4_10/raw/main/5732.bin",
    "id_bin": "5732",
    "list_language": [],
    "array_tags": [
      "digital",
      "analog",
      "floors",
      "weather",
      "steps"
    ],
    "list_album": [
      {
        "id_album": "1381221108",
        "link_thumb": "https://live.staticflickr.com/65535/51672093686_f430b32a56_o.gif",
        "title": "Football Old"
      }
    ]
  },
  {
    "author": "among",
    "link_thumb": "https://live.staticflickr.com/65535/51672352048_e6f43e8337_o.gif",
    "link_bin": "https://github.com/lmbstudiocontact/mb4_10/raw/main/5820.bin",
    "id_bin": "5820",
    "list_language": [],
    "array_tags": [
      "analog",
      "steps"
    ],
    "list_album": [
      {
        "id_album": "65078219",
        "link_thumb": "https://live.staticflickr.com/65535/51672352048_e6f43e8337_o.gif",
        "title": "Chibi"
      }
    ]
  },
  {
    "author": "among",
    "link_thumb": "https://live.staticflickr.com/65535/51672981010_8b6f8b00af_o.gif",
    "link_bin": "https://github.com/lmbstudiocontact/mb4_10/raw/main/5821.bin",
    "id_bin": "5821",
    "list_language": [],
    "array_tags": [
      "analog",
      "heartrate"
    ],
    "list_album": [
      {
        "id_album": "65078219",
        "link_thumb": "https://live.staticflickr.com/65535/51672981010_8b6f8b00af_o.gif",
        "title": "Chibi"
      }
    ]
  },
  {
    "author": "trankhanh567",
    "link_thumb": "https://live.staticflickr.com/65535/51671322147_6bb0d4da07_o.gif",
    "link_bin": "https://github.com/lmbstudiocontact/mb4_10/raw/main/59.bin",
    "id_bin": "59",
    "list_language": [],
    "array_tags": [
      "digital",
      "date",
      "distance",
      "miband4",
      "heartrate",
      "calories",
      "battery",
      "steps",
      "analog",
      "seconds",
      "floors",
      "weather",
      "pikachu"
    ],
    "list_album": [
      {
        "id_album": "63410260",
        "link_thumb": "https://live.staticflickr.com/65535/51671322147_6bb0d4da07_o.gif",
        "title": "Anime"
      }
    ]
  },
  {
    "author": "chanix002",
    "link_thumb": "https://live.staticflickr.com/65535/51672805914_36d544512b_o.gif",
    "link_bin": "https://github.com/lmbstudiocontact/mb4_10/raw/main/5933.bin",
    "id_bin": "5933",
    "list_language": [],
    "array_tags": [
      "digital",
      "date",
      "analog",
      "seconds",
      "floors",
      "distance",
      "heartrate",
      "weather",
      "battery"
    ],
    "list_album": [
      {
        "id_album": "224945075",
        "link_thumb": "https://live.staticflickr.com/65535/51672805914_36d544512b_o.gif",
        "title": "Cartoon_Animation"
      }
    ]
  },
  {
    "author": "f40423",
    "link_thumb": "https://live.staticflickr.com/65535/51672822554_cf83377a99_o.gif",
    "link_bin": "https://github.com/lmbstudiocontact/mb4_10/raw/main/6040.bin",
    "id_bin": "6040",
    "list_language": [],
    "array_tags": [
      "digital",
      "date",
      "analog",
      "battery",
      "steps"
    ],
    "list_album": [
      {
        "id_album": "63410260",
        "link_thumb": "https://live.staticflickr.com/65535/51672822554_cf83377a99_o.gif",
        "title": "Anime"
      }
    ]
  },
  {
    "author": "grknbrs",
    "link_thumb": "https://live.staticflickr.com/65535/51671349762_195dccdd63_o.gif",
    "link_bin": "https://github.com/lmbstudiocontact/mb4_10/raw/main/6104.bin",
    "id_bin": "6104",
    "list_language": [],
    "array_tags": [
      "digital",
      "analog",
      "distance",
      "heartrate",
      "weather",
      "calories"
    ],
    "list_album": [
      {
        "id_album": "1381221108",
        "link_thumb": "https://live.staticflickr.com/65535/51671349762_195dccdd63_o.gif",
        "title": "Football Old"
      }
    ]
  },
  {
    "author": "Jhonnyfc",
    "link_thumb": "https://live.staticflickr.com/65535/51672150946_a9871528c0_o.gif",
    "link_bin": "https://github.com/lmbstudiocontact/mb4_10/raw/main/6105.bin",
    "id_bin": "6105",
    "list_language": [],
    "array_tags": [
      "digital",
      "date",
      "analog",
      "seconds",
      "floors",
      "distance",
      "heartrate",
      "weather",
      "calories",
      "battery",
      "steps"
    ],
    "list_album": [
      {
        "id_album": "80085222",
        "link_thumb": "https://live.staticflickr.com/65535/51672150946_a9871528c0_o.gif",
        "title": "Space"
      }
    ]
  },
  {
    "author": "Thxamas",
    "link_thumb": "https://live.staticflickr.com/65535/51672837124_807721fd1d_o.gif",
    "link_bin": "https://github.com/lmbstudiocontact/mb4_10/raw/main/6168.bin",
    "id_bin": "6168",
    "list_language": [],
    "array_tags": [
      "date",
      "analog",
      "distance",
      "battery"
    ],
    "list_album": [
      {
        "id_album": "-1997428321",
        "link_thumb": "https://live.staticflickr.com/65535/51672837124_807721fd1d_o.gif",
        "title": "Marvel"
      }
    ]
  },
  {
    "author": "Thxamas",
    "link_thumb": "https://live.staticflickr.com/65535/51672158901_995d7a375b_o.gif",
    "link_bin": "https://github.com/lmbstudiocontact/mb4_10/raw/main/6170.bin",
    "id_bin": "6170",
    "list_language": [],
    "array_tags": [
      "date",
      "analog",
      "heartrate",
      "battery"
    ],
    "list_album": [
      {
        "id_album": "-1997428321",
        "link_thumb": "https://live.staticflickr.com/65535/51672158901_995d7a375b_o.gif",
        "title": "Marvel"
      }
    ]
  }
]